getpack/__init__.py
getpack/library/__init__.py
getpack-0.0.6.dist-info/LICENSE
getpack-0.0.6.dist-info/METADATA
getpack-0.0.6.dist-info/WHEEL
getpack-0.0.6.dist-info/top_level.txt
getpack-0.0.6.dist-info/RECORD
