Metadata-Version: 2.1
Name: getpack
Version: 0.0.6
Summary: Declarative external resources any with implicit deployment
Home-page: https://github.com/kalemas/getpack
Author: Konstantin Maslyuk
Author-email: Kostya.Maslyuk@gmail.com
Project-URL: Bug Tracker, https://github.com/kalemas/getpack/issues
Classifier: Programming Language :: Python :: 3
Classifier: License :: OSI Approved :: MIT License
Classifier: Operating System :: Microsoft :: Windows :: Windows 10
License-File: LICENSE
Provides-Extra: dev
Requires-Dist: flake8 ; extra == 'dev'
Requires-Dist: flake8-import-order ; extra == 'dev'
Requires-Dist: mypy ; extra == 'dev'
Requires-Dist: pytest ; extra == 'dev'
Requires-Dist: yapf ; extra == 'dev'
